mtmtrain/.vscode/extensions.json
mtmtrain/.vscode/keybindings.json
mtmtrain/.vscode/launch.json
mtmtrain/.vscode/mt.code-snippets
mtmtrain/.vscode/settings.json
mtmtrain/.vscode/tasks.json
mtmtrain/__init__.py
mtmtrain/__main__.py
mtmtrain/classify_demo.py
mtmtrain/core/__init__.py
mtmtrain/core/__version__.py
mtmtrain/core/config.py
mtmtrain/dataset.py
mtmtrain/env.py
mtmtrain/ipy/__init__.py
mtmtrain/ipy/ipyutils.py
mtmtrain/scripts/post_install.py
mtmtrain/setup.py
mtmtrain/text_classify/__init__.py
mtmtrain/text_classify/art_rewrite.py
mtmtrain/text_classify/demo1/README.md
mtmtrain/text_classify/demo1/RNNmodel.py
mtmtrain/text_classify/demo1/__init__.py
mtmtrain/text_classify/demo1/data_process_module.py
mtmtrain/text_classify/demo1/main.py
mtmtrain/text_classify/demo1/train_best_model.py
mtmtrain/text_classify/distilbert/TextClassificationWithBERT.ipynb
mtmtrain/text_classify/distilbert/distilbert copy.py
mtmtrain/text_classify/distilbert/distilbert.py
mtmtrain/text_classify/tests/text_classify_test.py
mtmtrain/text_classify/text_classify.py
mtmtrain/train_demos/__init__.py
mtmtrain/train_demos/bert.py
mtmtrain/train_demos/how_to_train.py
mtmtrain/train_demos/run_classification.py
mtmtrain/train_demos/train_example1.py
mtmtrain/train_demos/umlfit_example.py
mtmtrain/utils.py
mtmtrain/worker.py
mtmtrain-0.4.186.dist-info/METADATA
mtmtrain-0.4.186.dist-info/WHEEL
mtmtrain-0.4.186.dist-info/entry_points.txt
mtmtrain-0.4.186.dist-info/RECORD
