Metadata-Version: 2.1
Name: mtmtrain
Version: 0.4.186
Summary: 
License: MIT
Author: John Smith
Author-email: john@example.com
Requires-Python: >=3.10,<3.13
Classifier: License :: OSI Approved :: MIT License
Classifier: Programming Language :: Python :: 3
Classifier: Programming Language :: Python :: 3.10
Classifier: Programming Language :: Python :: 3.11
Classifier: Programming Language :: Python :: 3.12
Requires-Dist: datasets (>=2.21.0,<3.0.0)
Requires-Dist: evaluate (>=0.4.2,<0.5.0)
Requires-Dist: fastai (>=2.7.16,<3.0.0)
Requires-Dist: keras (>=3.5.0,<4.0.0)
Requires-Dist: matplotlib (>=3.9.2,<4.0.0)
Requires-Dist: mtmai-client (>=0.3.367,<0.4.0)
Requires-Dist: mtmlib (>=0.3.287,<0.4.0)
Requires-Dist: python-dotenv (>=1.0.1,<2.0.0)
Requires-Dist: scikit-learn (>=1.5.1,<2.0.0)
Requires-Dist: tensorflow (>=2.17.0,<3.0.0)
Requires-Dist: torch (>=2.3.1,<3.0.0)
Requires-Dist: transformers (>=4.44.2,<5.0.0)
